bw_libs/__init__.py
bw_libs/main.py
bw_libs-0.1.3.dist-info/LICENSE
bw_libs-0.1.3.dist-info/METADATA
bw_libs-0.1.3.dist-info/WHEEL
bw_libs-0.1.3.dist-info/top_level.txt
bw_libs-0.1.3.dist-info/RECORD
