Metadata-Version: 2.1
Name: bw-libs
Version: 0.1.3
Summary: DESCRIPTION
Author: Sargis
Author-email: <sargis@bridgewise.com>
Keywords: python
Classifier: Development Status :: 1 - Planning
Classifier: Intended Audience :: Developers
Classifier: Programming Language :: Python :: 3
Classifier: Operating System :: Unix
Classifier: Operating System :: MacOS :: MacOS X
Classifier: Operating System :: Microsoft :: Windows
License-File: LICENSE
Requires-Dist: pydantic
